dev_fancy_console/__init__.py
dev_fancy_console/fancy_message.py
dev_fancy_console/examples/__init__.py
dev_fancy_console/examples/ex_1.py
dev_fancy_console/examples/ex_2.py
dev_fancy_console/examples/ex_3.py
dev_fancy_console/examples/ex_4.py
dev_fancy_console/presets/__init__.py
dev_fancy_console/presets/fancy_background_colors.py
dev_fancy_console/presets/fancy_colors.py
dev_fancy_console/presets/fancy_styles.py
dev_fancy_console/presets/fancy_utilities.py
dev_fancy_console-0.0.1.dist-info/METADATA
dev_fancy_console-0.0.1.dist-info/WHEEL
dev_fancy_console-0.0.1.dist-info/entry_points.txt
dev_fancy_console-0.0.1.dist-info/top_level.txt
dev_fancy_console-0.0.1.dist-info/RECORD
