Metadata-Version: 2.1
Name: dev_fancy_console
Version: 0.0.1
Summary: Stylized Python console, a project made for fun
Home-page: https://github.com/SKoprek/python-fancy-console
Author: SKoprek
